container/__init__.py
container_py-0.0.0.dist-info/LICENSE.txt
container_py-0.0.0.dist-info/METADATA
container_py-0.0.0.dist-info/WHEEL
container_py-0.0.0.dist-info/top_level.txt
container_py-0.0.0.dist-info/RECORD
