Metadata-Version: 2.1
Name: container-py
Version: 0.0.0
Summary: the missing container python sdk
Home-page: https://github.com/danielbraun-org/container
Author: Daniel Braun
Author-email: braundaniel@live.com
License: UNKNOWN
Platform: UNKNOWN
License-File: LICENSE.txt
